{"content":"---\n# required metadata\n\ntitle: Product confirmation for cluster picking\ndescription: This topic describes how you set up item verificatin together with cluster picking.\nauthor: Mirzaab\nmanager: AnnBe\nms.date: 05/26/2017\nms.topic: article\nms.prod: \nms.service: dynamics-ax-applications\nms.technology: \n\n# optional metadata\n\n# ms.search.form:  WHSRFAutoConfirm\naudience: Application User\n# ms.devlang: \nms.reviewer: bis\nms.search.scope: Core, AX 7.0.0, Operations, UnifiedOperations\n# ms.tgt_pltfrm: \nms.custom: 269384\nms.search.region: Global\n# ms.search.industry: \nms.author: mirzaab\nms.search.validFrom: 2016-02-28\nms.dyn365.ops.version: AX 7.0.0\n\n---\n\n[!include[banner](../includes/banner.md)]\n\n# Product confirmation for cluster picking\nCluster picking allows you to pick items for several orders at the same time. When cluster picking is applied, item confirmation is crucial to verify the items that are added to clusters. You can verify items in cluster picking during the cluster picking process.\n\n## Where it applies\nItem verification for cluster picking works the same way as when you verify items in a non-cluster picking processes. The setup is based on the product bar code setup.\n\n## Set up item verification with cluster picking\n1.  On a mobile device menu item, open the setup form for work confirmation: **Warehouse management** > **Warehouse management** > **Setup** > **Mobile device** > **Mobile device menu items**.\n2.  From the mobile device menu item, open **Work confirmation setup**.\n\n| Option        | Description   | \n| ------------- | ------------- |\n|Product confirmation | Allows you to verify each piece of inventory from the mobile device when scanned.|\n","nodes":[{"pos":[4,649],"embed":true,"restype":"x-metadata","content":"# required metadata\n\ntitle: Product confirmation for cluster picking\ndescription: This topic describes how you set up item verificatin together with cluster picking.\nauthor: Mirzaab\nmanager: AnnBe\nms.date: 05/26/2017\nms.topic: article\nms.prod: \nms.service: dynamics-ax-applications\nms.technology: \n\n# optional metadata\n\n# ms.search.form:  WHSRFAutoConfirm\naudience: Application User\n# ms.devlang: \nms.reviewer: bis\nms.search.scope: Core, AX 7.0.0, Operations, UnifiedOperations\n# ms.tgt_pltfrm: \nms.custom: 269384\nms.search.region: Global\n# ms.search.industry: \nms.author: mirzaab\nms.search.validFrom: 2016-02-28\nms.dyn365.ops.version: AX 7.0.0\n","nodes":[{"content":"Product confirmation for cluster picking","nodes":[{"pos":[0,40],"content":"Product confirmation for cluster picking","nodes":[{"content":"Product confirmation for cluster picking","pos":[0,40]}]}],"path":["title"],"extradata":"MT"},{"content":"This topic describes how you set up item verificatin together with cluster picking.","nodes":[{"pos":[0,83],"content":"This topic describes how you set up item verificatin together with cluster picking.","nodes":[{"content":"This topic describes how you set up item verificatin together with cluster picking.","pos":[0,83]}]}],"path":["description"],"extradata":"MT"}],"header":"# required metadata\n","yml":true},{"pos":[700,740],"content":"Product confirmation for cluster picking","linkify":"Product confirmation for cluster picking","nodes":[{"content":"Product confirmation for cluster picking","pos":[0,40]}]},{"content":"Cluster picking allows you to pick items for several orders at the same time.","pos":[741,818]},{"content":"When cluster picking is applied, item confirmation is crucial to verify the items that are added to clusters.","pos":[819,928]},{"content":"You can verify items in cluster picking during the cluster picking process.","pos":[929,1004]},{"pos":[1009,1025],"content":"Where it applies","linkify":"Where it applies","nodes":[{"content":"Where it applies","pos":[0,16]}]},{"content":"Item verification for cluster picking works the same way as when you verify items in a non-cluster picking processes.","pos":[1026,1143]},{"content":"The setup is based on the product bar code setup.","pos":[1144,1193]},{"pos":[1198,1243],"content":"Set up item verification with cluster picking","linkify":"Set up item verification with cluster picking","nodes":[{"content":"Set up item verification with cluster picking","pos":[0,45]}]},{"pos":[1248,1436],"content":"On a mobile device menu item, open the setup form for work confirmation: <bpt id=\"p1\">**</bpt>Warehouse management<ept id=\"p1\">**</ept><ph id=\"ph1\"> &gt; </ph><bpt id=\"p2\">**</bpt>Warehouse management<ept id=\"p2\">**</ept><ph id=\"ph2\"> &gt; </ph><bpt id=\"p3\">**</bpt>Setup<ept id=\"p3\">**</ept><ph id=\"ph3\"> &gt; </ph><bpt id=\"p4\">**</bpt>Mobile device<ept id=\"p4\">**</ept><ph id=\"ph4\"> &gt; </ph><bpt id=\"p5\">**</bpt>Mobile device menu items<ept id=\"p5\">**</ept>.","source":"On a mobile device menu item, open the setup form for work confirmation: **Warehouse management** > **Warehouse management** > **Setup** > **Mobile device** > **Mobile device menu items**."},{"pos":[1441,1508],"content":"From the mobile device menu item, open <bpt id=\"p1\">**</bpt>Work confirmation setup<ept id=\"p1\">**</ept>.","source":"From the mobile device menu item, open **Work confirmation setup**."},{"content":"Option","pos":[1512,1518]},{"content":"Description","pos":[1528,1539]},{"content":"Product confirmation","pos":[1580,1600]},{"content":"Allows you to verify each piece of inventory from the mobile device when scanned.","pos":[1603,1684]}]}