{"content":"---\n# required metadata\n\ntitle: Code editor\ndescription: This article reviews the code editor features for Microsoft Dynamics 'AX 7.'\nauthor: RobinARH\nmanager: AnnBe\nms.date: 06/20/2017\nms.topic: article\nms.prod: \nms.service: dynamics-ax-platform\nms.technology: \n\n# optional metadata\n\n# ms.search.form: \n# ROBOTS: \naudience: Developer\n# ms.devlang: \nms.reviewer: robinr\nms.search.scope: AX 7.0.0, Operations, UnifiedOperations\n# ms.tgt_pltfrm: \nms.custom: 23941\nms.assetid: 87d75162-a9dd-43d2-a316-833e2c799f08\nms.search.region: Global\n# ms.search.industry: \nms.author: robadawy\nms.search.validFrom: 2016-02-28\nms.dyn365.ops.version: AX 7.0.0\n\n---\n\n# Code editor\n\n[!include[banner](../includes/banner.md)]\n\n\nThis article reviews the code editor features for Microsoft Dynamics 'AX 7.'\n\nCode editor\n-----------\n\nYou use the code editor in Microsoft Visual Studio to write the X++ code for your applications. The X++ language is fully integrated into the Visual Studio environment. As you write your X++ code, you will see the familiar features of the Visual Studio code editor. For example, IntelliSense is displayed to help you write the code. You can also navigate to methods and classes in the code editor by using the navigation drop-down menus at the top of the code editor window. \n\n![DevoToolsConcept](./media/31_devotoolsconcept.png) \n\nOther features, such as collapsible sections, are also available.\n\n### Opening the element designer\n\nYou can open the element designer that corresponds to the current X++ source code by right-clicking in the code editor and then selecting **Open Designer**. \n\n![opendesigner](./media/opendesigner.jpg)\n\n# See also\n\n[Developer home page](developer-home-page.md)\n\n[Development tools overview](development-tools-overview.md)\n\n\n\n","nodes":[{"pos":[4,643],"embed":true,"restype":"x-metadata","content":"# required metadata\n\ntitle: Code editor\ndescription: This article reviews the code editor features for Microsoft Dynamics 'AX 7.'\nauthor: RobinARH\nmanager: AnnBe\nms.date: 06/20/2017\nms.topic: article\nms.prod: \nms.service: dynamics-ax-platform\nms.technology: \n\n# optional metadata\n\n# ms.search.form: \n# ROBOTS: \naudience: Developer\n# ms.devlang: \nms.reviewer: robinr\nms.search.scope: AX 7.0.0, Operations, UnifiedOperations\n# ms.tgt_pltfrm: \nms.custom: 23941\nms.assetid: 87d75162-a9dd-43d2-a316-833e2c799f08\nms.search.region: Global\n# ms.search.industry: \nms.author: robadawy\nms.search.validFrom: 2016-02-28\nms.dyn365.ops.version: AX 7.0.0\n","nodes":[{"content":"Code editor","nodes":[{"pos":[0,11],"content":"Code editor","nodes":[{"content":"Code editor","pos":[0,11]}]}],"path":["title"],"extradata":"MT"},{"content":"This article reviews the code editor features for Microsoft Dynamics 'AX 7.'","nodes":[{"pos":[0,76],"content":"This article reviews the code editor features for Microsoft Dynamics 'AX 7.'","nodes":[{"content":"This article reviews the code editor features for Microsoft Dynamics 'AX 7.'","pos":[0,76]}]}],"path":["description"],"extradata":"MT"}],"header":"# required metadata\n","yml":true},{"pos":[651,662],"content":"Code editor","linkify":"Code editor","nodes":[{"content":"Code editor","pos":[0,11]}]},{"content":"This article reviews the code editor features for Microsoft Dynamics 'AX 7.'","pos":[708,784]},{"pos":[786,797],"content":"Code editor","linkify":"Code editor","nodes":[{"content":"Code editor","pos":[0,11]}]},{"content":"You use the code editor in Microsoft Visual Studio to write the X++ code for your applications.","pos":[811,906]},{"content":"The X++ language is fully integrated into the Visual Studio environment.","pos":[907,979]},{"content":"As you write your X++ code, you will see the familiar features of the Visual Studio code editor.","pos":[980,1076]},{"content":"For example, IntelliSense is displayed to help you write the code.","pos":[1077,1143]},{"content":"You can also navigate to methods and classes in the code editor by using the navigation drop-down menus at the top of the code editor window.","pos":[1144,1285]},{"content":"DevoToolsConcept","pos":[1290,1306]},{"content":"Other features, such as collapsible sections, are also available.","pos":[1343,1408]},{"pos":[1414,1442],"content":"Opening the element designer","linkify":"Opening the element designer","nodes":[{"content":"Opening the element designer","pos":[0,28]}]},{"pos":[1444,1600],"content":"You can open the element designer that corresponds to the current X++ source code by right-clicking in the code editor and then selecting <bpt id=\"p1\">**</bpt>Open Designer<ept id=\"p1\">**</ept>.","source":"You can open the element designer that corresponds to the current X++ source code by right-clicking in the code editor and then selecting **Open Designer**."},{"content":"opendesigner","pos":[1605,1617]},{"pos":[1648,1656],"content":"See also","linkify":"See also","nodes":[{"content":"See also","pos":[0,8]}]},{"pos":[1658,1703],"content":"<bpt id=\"p1\">[</bpt>Developer home page<ept id=\"p1\">](developer-home-page.md)</ept>","source":"[Developer home page](developer-home-page.md)"},{"pos":[1705,1764],"content":"<bpt id=\"p1\">[</bpt>Development tools overview<ept id=\"p1\">](development-tools-overview.md)</ept>","source":"[Development tools overview](development-tools-overview.md)"}]}